notool/__init__.py
notool/data_container.py
notool/dataclass_ex.py
notool/enum_ex.py
notool/helpers.py
notool/utils.py
notool-0.1.3.dist-info/LICENSE
notool-0.1.3.dist-info/METADATA
notool-0.1.3.dist-info/WHEEL
notool-0.1.3.dist-info/top_level.txt
notool-0.1.3.dist-info/RECORD
